quantspace/anomaly/__init__.py
quantspace/anomaly/_detect.py
quantspace/datasets/__init__.py
quantspace/datasets/_load_datasets.py
quantspace/plots/__init__.py
quantspace/plots/_plots_anomalies.py
quantspace/plots/_plots_risk.py
quantspace/portfolio/__init__.py
quantspace/portfolio/_methods.py
quantspace/risk/__init__.py
quantspace/risk/_metrics.py
quantspace/risk/_tables.py
quantspace/utils/anomaly/__init__.py
quantspace/utils/anomaly/_models.py
quantspace/utils/datasets/__init__.py
quantspace/utils/datasets/_randomdata.py
quantspace/utils/optimize/__init__.py
quantspace/utils/risk/__init__.py
quantspace-0.1.1.dist-info/LICENSE
quantspace-0.1.1.dist-info/METADATA
quantspace-0.1.1.dist-info/WHEEL
quantspace-0.1.1.dist-info/RECORD
