Metadata-Version: 2.1
Name: quantspace
Version: 0.1.1
Summary: Quantitative finance solutions in Python
Author: quantspace team
Maintainer: quantspace
Maintainer-email: contact@quantspaceai.com
Requires-Python: >=3.8,<4.0.0
Classifier: Programming Language :: Python :: 3
Classifier: Programming Language :: Python :: 3.8
Classifier: Programming Language :: Python :: 3.9
Classifier: Programming Language :: Python :: 3.10
Classifier: Programming Language :: Python :: 3.11
Classifier: Programming Language :: Python :: 3.12
Requires-Dist: autograd (>=1.6.2)
Requires-Dist: cvxopt (>=1.2.2)
Requires-Dist: matplotlib (>=3.7.2)
Requires-Dist: seaborn (>=0.11.2)
Requires-Dist: tqdm (>=4.64.1)
